davidkhala/data/format/arrow/__init__.py
davidkhala/data/format/arrow/fs.py
davidkhala/data/format/arrow/gcp.py
davidkhala/data/format/arrow/local_fs.py
davidkhala/data/format/avro/__init__.py
davidkhala/data/format/parquet/__init__.py
davidkhala/data/format/transform/__init__.py
davidkhala_data_format-0.0.5.dist-info/METADATA
davidkhala_data_format-0.0.5.dist-info/WHEEL
davidkhala_data_format-0.0.5.dist-info/RECORD
